syncro_api_ctek/__init__.py
syncro_api_ctek/assets.py
syncro_api_ctek/contacts.py
syncro_api_ctek/customers.py
syncro_api_ctek/invoices.py
syncro_api_ctek/ticket_timers.py
syncro_api_ctek/tickets.py
syncro_api_ctek-0.0.82.dist-info/licenses/LICENSE
syncro_api_ctek-0.0.82.dist-info/METADATA
syncro_api_ctek-0.0.82.dist-info/WHEEL
syncro_api_ctek-0.0.82.dist-info/top_level.txt
syncro_api_ctek-0.0.82.dist-info/RECORD
